azreaal
