Metadata-Version: 2.1
Name: azreaal
Version: 0.2
Summary: Custom Packages for Azreaal
Home-page: UNKNOWN
Author-email: azreaal42@gmail.com
License: UNKNOWN
Platform: UNKNOWN
